clitt/.version
clitt/__classpath__.py
clitt/__init__.py
clitt/__main__.py
clitt/welcome.txt
clitt/addons/__init__.py
clitt/addons/appman/__init__.py
clitt/addons/appman/appman.py
clitt/addons/appman/appman_enums.py
clitt/addons/appman/templates/__init__.py
clitt/addons/appman/templates/build.gradle.tpl
clitt/addons/appman/templates/classpath.py.tpl
clitt/addons/appman/templates/dependencies.hspd.tpl
clitt/addons/appman/templates/gitignore.tpl
clitt/addons/appman/templates/main.py.tpl
clitt/addons/appman/templates/main_qt.py.tpl
clitt/addons/appman/templates/main_qt_view.py.tpl
clitt/addons/appman/templates/main_qt_view.ui.tpl
clitt/addons/appman/templates/run.sh.tpl
clitt/addons/appman/templates/test_main.py.tpl
clitt/addons/appman/templates/usage.txt.tpl
clitt/addons/appman/templates/widget.py.tpl
clitt/addons/appman/templates/__pycache__/__init__.cpython-311.pyc
clitt/addons/widman/__init__.py
clitt/addons/widman/widget.py
clitt/addons/widman/widget_entry.py
clitt/addons/widman/widman.py
clitt/addons/widman/widgets/__init__.py
clitt/addons/widman/widgets/widget_free.py
clitt/addons/widman/widgets/widget_punch.py
clitt/addons/widman/widgets/widget_send_msg.py
clitt/addons/widman/widgets/widget_time_calc.py
clitt/core/__init__.py
clitt/core/preferences.py
clitt/core/exception/__init__.py
clitt/core/exception/exceptions.py
clitt/core/icons/__init__.py
clitt/core/icons/emojis/__init__.py
clitt/core/icons/emojis/emojis.py
clitt/core/icons/emojis/face_smiling.py
clitt/core/icons/font_awesome/__init__.py
clitt/core/icons/font_awesome/app_icons.py
clitt/core/icons/font_awesome/awesome.py
clitt/core/icons/font_awesome/dashboard_icons.py
clitt/core/icons/font_awesome/form_icons.py
clitt/core/icons/font_awesome/game_icons.py
clitt/core/icons/font_awesome/nav_icons.py
clitt/core/icons/font_awesome/trickplay_icons.py
clitt/core/icons/font_awesome/widget_icons.py
clitt/core/term/__init__.py
clitt/core/term/commons.py
clitt/core/term/cursor.py
clitt/core/term/screen.py
hspylib_clitt-0.9.151.dist-info/METADATA
hspylib_clitt-0.9.151.dist-info/WHEEL
hspylib_clitt-0.9.151.dist-info/top_level.txt
hspylib_clitt-0.9.151.dist-info/RECORD
