Metadata-Version: 2.4
Name: hspylib-clitt
Version: 0.9.151
Summary: HsPyLib - CLI Terminal Tools
Home-page: https://github.com/yorevs/hspylib
Author: Hugo Saporetti Junior
Author-email: yorevs@hotmail.com
License: MIT
Project-URL: GitHub, https://github.com/yorevs/hspylib
Project-URL: PyPi, https://pypi.org/project/hspylib-clitt/
Keywords: cli,clitt,terminal,tui,manager,application,widgets
Platform: Darwin
Platform: Linux
Classifier: License :: OSI Approved :: MIT License
Classifier: Programming Language :: Python :: 3.10
Classifier: Operating System :: MacOS :: MacOS X
Classifier: Operating System :: POSIX :: Linux
Classifier: Operating System :: Unix
Classifier: Development Status :: 3 - Alpha
Classifier: Environment :: Console
Classifier: Natural Language :: English
Classifier: Topic :: Terminals
Classifier: Topic :: Software Development :: Libraries :: Python Modules
Classifier: Topic :: Software Development :: Libraries :: Application Frameworks
Classifier: Intended Audience :: Developers
Requires-Python: >=3.10
Requires-Dist: hspylib
Requires-Dist: pyperclip>=1.11.0
Requires-Dist: urllib3>=1.26.20
Requires-Dist: emoji>=2.12.1
Requires-Dist: rich>=14.2.0
Dynamic: author
Dynamic: author-email
Dynamic: classifier
Dynamic: description
Dynamic: description-content-type
Dynamic: home-page
Dynamic: keywords
Dynamic: license
Dynamic: platform
Dynamic: project-url
Dynamic: requires-dist
Dynamic: requires-python
Dynamic: summary
